stellar_plots/__init__.py
stellar_plots/driver.py
stellar_plots/make_plot.py
stellar_plots/mast_utils.py
stellar_plots/utils.py
stellar_plots-0.0.3.dist-info/LICENSE.md
stellar_plots-0.0.3.dist-info/METADATA
stellar_plots-0.0.3.dist-info/WHEEL
stellar_plots-0.0.3.dist-info/top_level.txt
stellar_plots-0.0.3.dist-info/RECORD
